amd_hipmm/__init__.py
amd_hipmm-0.0.2.dist-info/METADATA
amd_hipmm-0.0.2.dist-info/WHEEL
amd_hipmm-0.0.2.dist-info/top_level.txt
amd_hipmm-0.0.2.dist-info/RECORD
