Metadata-Version: 2.4
Name: amd-hipmm
Version: 0.0.2
Summary: hipMM - Memory Manager for AMD GPUs
Author-email: AMD <support@amd.com>
License: Apache 2.0 AND MIT
Project-URL: Homepage, https://github.com/rocm/hipmm
Requires-Python: >=3.8
